Shannon Rhodes - Compiler Construction - Project 4 - 4/26/15
--------------------------------------------------------------
arith.c
--------------------------------------------------------------
PURPOSE: test global variables, printf, and additive statement
OUTCOME:
.source Main.java
.class  synchronized Main
.super  java/lang/Object

.field static x I
.field static y I
.field static sum I
; >>FUNCTION MAIN <<
.method public static main([Ljava/lang/String;)V
.throws java/io/IOException
.limit stack 32
.limit locals 32
getstatic Main/x I
ldc 2
isub
putstatic Main/x I
getstatic Main/y I
ldc 3
iadd
putstatic Main/y I
getstatic Main/sum I
getstatic Main/x I
isub
getstatic Main/y I
isub
ldc 4
iadd
putstatic Main/sum I
getstatic Main/sum I
getstatic Main/sum I
imul
getstatic Main/y I
idiv
putstatic Main/sum I
getstatic java/lang/System/out Ljava/io/PrintStream;
getstatic Main/sum I
invokevirtual java/io/PrintStream/println(I)V
return
.end method

; >> CONSTRUCTOR <<
.method <init>()V
.limit stack 1
.limit locals 1
aload_0
invokenonvirtual java/lang/Object/<init>()V
return
.end method

; >> CLASS INIT FOR GLOBAL ARRAYS <<
.method static <clinit>()V
.limit stack 1
.limit locals 0
return
.end method
--------------------------------------------------------------
arr1.c
--------------------------------------------------------------
PURPOSE: test for global array declarations
OUTCOME:
.source Main.java
.class  synchronized Main
.super  java/lang/Object

.field static y [I
; >>FUNCTION MAIN <<
.method public static main([Ljava/lang/String;)V
.throws java/io/IOException
.limit stack 32
.limit locals 32
getstatic Main/y [I
ldc 2
ldc 5
iastore 
getstatic java/lang/System/out Ljava/io/PrintStream;
getstatic Main/y [I
ldc 2
iaload 
invokevirtual java/io/PrintStream/println(I)V
return
.end method

; >> CONSTRUCTOR <<
.method <init>()V
.limit stack 1
.limit locals 1
aload_0
invokenonvirtual java/lang/Object/<init>()V
return
.end method

; >> CLASS INIT FOR GLOBAL ARRAYS <<
.method static <clinit>()V
.limit stack 1
.limit locals 0
ldc 10
newarray int
putstatic Main/y [I
return
.end method
--------------------------------------------------------------
arr2.c
--------------------------------------------------------------
PURPOSE: test function with code in it, and function call
OUTCOME:
.source Main.java
.class  synchronized Main
.super  java/lang/Object

; >> FUNCTION f <<
.method static f()V
.limit stack 32
.limit locals 32
ldc 10
newarray int
astore 0
aload 0
ldc 5
ldc 10
iastore 
getstatic java/lang/System/out Ljava/io/PrintStream;
aload 0
ldc 5
iaload 
invokevirtual java/io/PrintStream/println(I)V
return
.end method

; >>FUNCTION MAIN <<
.method public static main([Ljava/lang/String;)V
.throws java/io/IOException
.limit stack 32
.limit locals 32
invokestatic Main/f()V
return
.end method

; >> CONSTRUCTOR <<
.method <init>()V
.limit stack 1
.limit locals 1
aload_0
invokenonvirtual java/lang/Object/<init>()V
return
.end method

; >> CLASS INIT FOR GLOBAL ARRAYS <<
.method static <clinit>()V
.limit stack 1
.limit locals 0
return
.end method
--------------------------------------------------------------
arr3.c
--------------------------------------------------------------
PURPOSE:test for global variable and array
OUTCOME:
.source Main.java
.class  synchronized Main
.super  java/lang/Object

.field static x I
.field static y [I
; >>FUNCTION MAIN <<
.method public static main([Ljava/lang/String;)V
.throws java/io/IOException
.limit stack 32
.limit locals 32
getstatic Main/y [I
ldc 2
ldc 7
iastore 
getstatic Main/y [I
ldc 2
iaload 
putstatic Main/x I
getstatic java/lang/System/out Ljava/io/PrintStream;
getstatic Main/x I
invokevirtual java/io/PrintStream/println(I)V
return
.end method

; >> CONSTRUCTOR <<
.method <init>()V
.limit stack 1
.limit locals 1
aload_0
invokenonvirtual java/lang/Object/<init>()V
return
.end method

; >> CLASS INIT FOR GLOBAL ARRAYS <<
.method static <clinit>()V
.limit stack 1
.limit locals 0
ldc 10
newarray int
putstatic Main/y [I
return
.end method
--------------------------------------------------------------
bsort.c - parameter not correct for arrays
--------------------------------------------------------------
PURPOSE: test nested loops, dealing with arrays
OUTCOME:
.source Main.java
.class  synchronized Main
.super  java/lang/Object

.field static max I
; >> FUNCTION bubbleSort <<
.method static bubbleSort(II)V
.limit stack 32
.limit locals 32
ldc 0
istore 2
Label1:
iload 2
iload 1
if_icmplt Label2
ldc 0
goto Label3
Label2:
ldc 1
Label3:
ifeq Label4
ldc 1
istore 3
Label5:
iload 3
iload 1
iload 2
isub
if_icmplt Label6
ldc 0
goto Label7
Label6:
ldc 1
Label7:
ifeq Label8
aload 0
iload 3
ldc 1
isub
iaload 
aload 0
iload 3
iaload 
if_icmpgt Label9
ldc 0
goto Label10
Label9:
ldc 1
Label10:
ifeq Label11
aload 0
iload 3
ldc 1
isub
iaload 
istore 4
aload 0
iload 3
ldc 1
isub
aload 0
iload 3
iaload 
iastore 
aload 0
iload 3
iload 4
iastore 
goto Label12
Label11:
Label12:
iload 3
ldc 1
iadd
istore 3
goto Label5
Label8:
iload 2
ldc 1
iadd
istore 2
goto Label1
Label4:
return
.end method

; >> FUNCTION printArray <<
.method static printArray(I)V
.limit stack 32
.limit locals 32
ldc 0
istore 1
Label13:
iload 1
getstatic Main/max I
if_icmplt Label14
ldc 0
goto Label15
Label14:
ldc 1
Label15:
ifeq Label16
getstatic java/lang/System/out Ljava/io/PrintStream;
aload 0
iload 1
iaload 
invokevirtual java/io/PrintStream/println(I)V
iload 1
ldc 1
iadd
istore 1
goto Label13
Label16:
return
.end method

; >>FUNCTION MAIN <<
.method public static main([Ljava/lang/String;)V
.throws java/io/IOException
.limit stack 32
.limit locals 32
ldc 8
newarray int
astore 1
ldc 8
putstatic Main/max I
aload 1
ldc 0
ldc 12
iastore 
aload 1
ldc 1
ldc 9
iastore 
aload 1
ldc 2
ldc 4
iastore 
aload 1
ldc 3
ldc 99
iastore 
aload 1
ldc 4
ldc 120
iastore 
aload 1
ldc 5
ldc 1
iastore 
aload 1
ldc 6
ldc 3
iastore 
aload 1
ldc 7
ldc 10
iastore 
iload 1
invokestatic Main/printArray(I)V
iload 1
getstatic Main/max I
invokestatic Main/bubbleSort(II)V
iload 1
invokestatic Main/printArray(I)V
return
.end method

; >> CONSTRUCTOR <<
.method <init>()V
.limit stack 1
.limit locals 1
aload_0
invokenonvirtual java/lang/Object/<init>()V
return
.end method

; >> CLASS INIT FOR GLOBAL ARRAYS <<
.method static <clinit>()V
.limit stack 1
.limit locals 0
return
.end method
--------------------------------------------------------------
bsorti.c - array parameter issues
--------------------------------------------------------------
PURPOSE: test scanf and nested while and if statements
OUTCOME:
.source Main.java
.class  synchronized Main
.super  java/lang/Object

.field static max I
; >> FUNCTION bubbleSort <<
.method static bubbleSort(II)V
.limit stack 32
.limit locals 32
ldc 0
istore 2
Label1:
iload 2
iload 1
if_icmplt Label2
ldc 0
goto Label3
Label2:
ldc 1
Label3:
ifeq Label4
ldc 1
istore 3
Label5:
iload 3
iload 1
iload 2
isub
if_icmplt Label6
ldc 0
goto Label7
Label6:
ldc 1
Label7:
ifeq Label8
aload 0
iload 3
ldc 1
isub
iaload 
aload 0
iload 3
iaload 
if_icmpgt Label9
ldc 0
goto Label10
Label9:
ldc 1
Label10:
ifeq Label11
aload 0
iload 3
ldc 1
isub
iaload 
istore 4
aload 0
iload 3
ldc 1
isub
aload 0
iload 3
iaload 
iastore 
aload 0
iload 3
iload 4
iastore 
goto Label12
Label11:
Label12:
iload 3
ldc 1
iadd
istore 3
goto Label5
Label8:
iload 2
ldc 1
iadd
istore 2
goto Label1
Label4:
return
.end method

; >> FUNCTION printArray <<
.method static printArray(I)V
.limit stack 32
.limit locals 32
ldc 0
istore 1
Label13:
iload 1
getstatic Main/max I
if_icmplt Label14
ldc 0
goto Label15
Label14:
ldc 1
Label15:
ifeq Label16
getstatic java/lang/System/out Ljava/io/PrintStream;
aload 0
iload 1
iaload 
invokevirtual java/io/PrintStream/println(I)V
iload 1
ldc 1
iadd
istore 1
goto Label13
Label16:
return
.end method

; >> FUNCTION readArray <<
.method static readArray(I)V
.limit stack 32
.limit locals 32
ldc 0
istore 2
ldc 0
istore 1
getstatic java/lang/System/out Ljava/io/PrintStream;
getstatic Main/max I
invokevirtual java/io/PrintStream/println(I)V
Label17:
iload 1
getstatic Main/max I
if_icmplt Label18
ldc 0
goto Label19
Label18:
ldc 1
Label19:
ifeq Label20
invokestatic Main/myRead()I
istore 2
aload 0
iload 1
iload 2
iastore 
iload 1
ldc 1
iadd
istore 1
goto Label17
Label20:
return
.end method

; >>FUNCTION MAIN <<
.method public static main([Ljava/lang/String;)V
.throws java/io/IOException
.limit stack 32
.limit locals 32
ldc 8
newarray int
astore 1
ldc 8
putstatic Main/max I
iload 1
invokestatic Main/readArray(I)V
iload 1
getstatic Main/max I
invokestatic Main/bubbleSort(II)V
iload 1
invokestatic Main/printArray(I)V
return
.end method

; >> READ METHOD <<
.method private static myRead()I
.throws java/io/IOException

.limit stack 5
.limit locals 2

new java/io/BufferedReader
dup
new java/io/InputStreamReader
dup
getstatic java/lang/System/in Ljava/io/InputStream;
invokenonvirtual java/io/InputStreamReader/<init>(Ljava/io/InputStream;)V
invokenonvirtual java/io/BufferedReader/<init>(Ljava/io/Reader;)V
astore_0
aload_0
invokevirtual java/io/BufferedReader/readLine()Ljava/lang/String;
astore_1
aload_1
invokestatic java/lang/Integer/parseInt(Ljava/lang/String;)I
ireturn
.end method

; >> CONSTRUCTOR <<
.method <init>()V
.limit stack 1
.limit locals 1
aload_0
invokenonvirtual java/lang/Object/<init>()V
return
.end method

; >> CLASS INIT FOR GLOBAL ARRAYS <<
.method static <clinit>()V
.limit stack 1
.limit locals 0
return
.end method
--------------------------------------------------------------
fact.c - redeclared global variable problem
hash table has two X when we try to search for that global variable the hash function ends at the first X even though that X is marked invalid. This causes our JVM code to use istore instead of putStatic. 
--------------------------------------------------------------
PURPOSE:
OUTCOME:
.source Main.java
.class  synchronized Main
.super  java/lang/Object

.field static x I
; >> FUNCTION f <<
.method static f(I)V
.limit stack 32
.limit locals 32
iload 0
ldc 1
if_icmple Label1
ldc 0
goto Label2
Label1:
ldc 1
Label2:
ifeq Label3
ldc 1
istore 1
goto Label4
Label3:
iload 0
iload 0
ldc 1
isub
invokestatic Main/f(I)I
imul
istore 1
Label4:
iload 1
ireturn
return
.end method

; >>FUNCTION MAIN <<
.method public static main([Ljava/lang/String;)V
.throws java/io/IOException
.limit stack 32
.limit locals 32
ldc 5
istore 0
getstatic java/lang/System/out Ljava/io/PrintStream;
iload 0
invokestatic Main/f(I)I
invokevirtual java/io/PrintStream/println(I)V
return
.end method

; >> CONSTRUCTOR <<
.method <init>()V
.limit stack 1
.limit locals 1
aload_0
invokenonvirtual java/lang/Object/<init>()V
return
.end method

; >> CLASS INIT FOR GLOBAL ARRAYS <<
.method static <clinit>()V
.limit stack 1
.limit locals 0
return
.end method
--------------------------------------------------------------
func1.c - 
--------------------------------------------------------------
PURPOSE: test calling a function
OUTCOME:
.source Main.java
.class  synchronized Main
.super  java/lang/Object

.field static x I
; >> FUNCTION f <<
.method static f(I)V
.limit stack 32
.limit locals 32
iload 0
putstatic Main/x I
return
.end method

; >>FUNCTION MAIN <<
.method public static main([Ljava/lang/String;)V
.throws java/io/IOException
.limit stack 32
.limit locals 32
ldc 20
invokestatic Main/f(I)V
getstatic java/lang/System/out Ljava/io/PrintStream;
getstatic Main/x I
invokevirtual java/io/PrintStream/println(I)V
return
.end method

; >> CONSTRUCTOR <<
.method <init>()V
.limit stack 1
.limit locals 1
aload_0
invokenonvirtual java/lang/Object/<init>()V
return
.end method

; >> CLASS INIT FOR GLOBAL ARRAYS <<
.method static <clinit>()V
.limit stack 1
.limit locals 0
return
.end method
--------------------------------------------------------------
func2.c
--------------------------------------------------------------
PURPOSE: test an empty function call, global variable, printf
OUTCOME:
.source Main.java
.class  synchronized Main
.super  java/lang/Object

.field static x I
; >> FUNCTION incX <<
.method static incX()V
.limit stack 32
.limit locals 32
getstatic Main/x I
ldc 1
iadd
putstatic Main/x I
return
.end method

; >>FUNCTION MAIN <<
.method public static main([Ljava/lang/String;)V
.throws java/io/IOException
.limit stack 32
.limit locals 32
ldc 1
putstatic Main/x I
invokestatic Main/incX()V
getstatic java/lang/System/out Ljava/io/PrintStream;
getstatic Main/x I
invokevirtual java/io/PrintStream/println(I)V
return
.end method

; >> CONSTRUCTOR <<
.method <init>()V
.limit stack 1
.limit locals 1
aload_0
invokenonvirtual java/lang/Object/<init>()V
return
.end method

; >> CLASS INIT FOR GLOBAL ARRAYS <<
.method static <clinit>()V
.limit stack 1
.limit locals 0
return
.end method
--------------------------------------------------------------
func3.c
--------------------------------------------------------------
PURPOSE: test calling a function in a print statement, integer function
OUTCOME:
.source Main.java
.class  synchronized Main
.super  java/lang/Object

; >> FUNCTION f <<
.method static f()V
.limit stack 32
.limit locals 32
ldc 20
ireturn
return
.end method

; >>FUNCTION MAIN <<
.method public static main([Ljava/lang/String;)V
.throws java/io/IOException
.limit stack 32
.limit locals 32
getstatic java/lang/System/out Ljava/io/PrintStream;
invokestatic Main/f()I
invokevirtual java/io/PrintStream/println(I)V
return
.end method

; >> CONSTRUCTOR <<
.method <init>()V
.limit stack 1
.limit locals 1
aload_0
invokenonvirtual java/lang/Object/<init>()V
return
.end method

; >> CLASS INIT FOR GLOBAL ARRAYS <<
.method static <clinit>()V
.limit stack 1
.limit locals 0
return
.end method
--------------------------------------------------------------
func4.c
--------------------------------------------------------------
PURPOSE: check while loop and additive statements
OUTCOME:
.source Main.java
.class  synchronized Main
.super  java/lang/Object

; >> FUNCTION sum <<
.method static sum()V
.limit stack 32
.limit locals 32
ldc 0
istore 1
ldc 1
istore 0
Label1:
iload 0
ldc 10
if_icmple Label2
ldc 0
goto Label3
Label2:
ldc 1
Label3:
ifeq Label4
iload 1
iload 0
iadd
istore 1
iload 0
ldc 1
iadd
istore 0
goto Label1
Label4:
getstatic java/lang/System/out Ljava/io/PrintStream;
iload 1
invokevirtual java/io/PrintStream/println(I)V
return
.end method

; >>FUNCTION MAIN <<
.method public static main([Ljava/lang/String;)V
.throws java/io/IOException
.limit stack 32
.limit locals 32
invokestatic Main/sum()V
return
.end method

; >> CONSTRUCTOR <<
.method <init>()V
.limit stack 1
.limit locals 1
aload_0
invokenonvirtual java/lang/Object/<init>()V
return
.end method

; >> CLASS INIT FOR GLOBAL ARRAYS <<
.method static <clinit>()V
.limit stack 1
.limit locals 0
return
.end method
--------------------------------------------------------------
func5.c
--------------------------------------------------------------
PURPOSE: calling function in print statement, while statement, returning integer
OUTCOME:
.source Main.java
.class  synchronized Main
.super  java/lang/Object

; >> FUNCTION sum <<
.method static sum(I)V
.limit stack 32
.limit locals 32
ldc 0
istore 2
ldc 0
istore 1
Label1:
iload 1
iload 0
if_icmple Label2
ldc 0
goto Label3
Label2:
ldc 1
Label3:
ifeq Label4
iload 2
iload 1
iadd
istore 2
iload 1
ldc 1
iadd
istore 1
goto Label1
Label4:
iload 2
ireturn
return
.end method

; >>FUNCTION MAIN <<
.method public static main([Ljava/lang/String;)V
.throws java/io/IOException
.limit stack 32
.limit locals 32
getstatic java/lang/System/out Ljava/io/PrintStream;
ldc 20
invokestatic Main/sum(I)I
invokevirtual java/io/PrintStream/println(I)V
return
.end method

; >> CONSTRUCTOR <<
.method <init>()V
.limit stack 1
.limit locals 1
aload_0
invokenonvirtual java/lang/Object/<init>()V
return
.end method

; >> CLASS INIT FOR GLOBAL ARRAYS <<
.method static <clinit>()V
.limit stack 1
.limit locals 0
return
.end method
--------------------------------------------------------------
gcd.c 
--------------------------------------------------------------
PURPOSE: nested If statements
OUTCOME:
.source Main.java
.class  synchronized Main
.super  java/lang/Object

.field static n I
.field static m I
; >> FUNCTION gcd <<
.method static gcd(II)V
.limit stack 32
.limit locals 32
iload 1
ldc 0
if_icmpeq Label1
ldc 0
goto Label2
Label1:
ldc 1
Label2:
ifeq Label3
iload 0
istore 2
goto Label4
Label3:
iload 0
iload 1
if_icmplt Label5
ldc 0
goto Label6
Label5:
ldc 1
Label6:
ifeq Label7
iload 0
iload 1
iload 0
isub
invokestatic Main/gcd(II)I
istore 2
goto Label8
Label7:
iload 1
iload 0
iload 1
isub
invokestatic Main/gcd(II)I
istore 2
Label8:
Label4:
iload 2
ireturn
return
.end method

; >>FUNCTION MAIN <<
.method public static main([Ljava/lang/String;)V
.throws java/io/IOException
.limit stack 32
.limit locals 32
ldc 10
putstatic Main/n I
ldc 15
putstatic Main/m I
getstatic java/lang/System/out Ljava/io/PrintStream;
getstatic Main/n I
getstatic Main/m I
invokestatic Main/gcd(II)I
invokevirtual java/io/PrintStream/println(I)V
return
.end method

; >> CONSTRUCTOR <<
.method <init>()V
.limit stack 1
.limit locals 1
aload_0
invokenonvirtual java/lang/Object/<init>()V
return
.end method

; >> CLASS INIT FOR GLOBAL ARRAYS <<
.method static <clinit>()V
.limit stack 1
.limit locals 0
return
.end method
--------------------------------------------------------------
gcdi.c
--------------------------------------------------------------
PURPOSE: test for Scanf, functions with parameters
OUTCOME:
.source Main.java
.class  synchronized Main
.super  java/lang/Object

; >> FUNCTION gcd <<
.method static gcd(II)V
.limit stack 32
.limit locals 32
iload 1
ldc 0
if_icmpeq Label1
ldc 0
goto Label2
Label1:
ldc 1
Label2:
ifeq Label3
iload 0
ireturn
goto Label4
Label3:
iload 1
iload 0
iload 0
iload 1
idiv
iload 1
imul
isub
invokestatic Main/gcd(II)I
ireturn
Label4:
return
.end method

; >>FUNCTION MAIN <<
.method public static main([Ljava/lang/String;)V
.throws java/io/IOException
.limit stack 32
.limit locals 32
invokestatic Main/myRead()I
istore 1
invokestatic Main/myRead()I
istore 2
getstatic java/lang/System/out Ljava/io/PrintStream;
iload 1
iload 2
invokestatic Main/gcd(II)I
invokevirtual java/io/PrintStream/println(I)V
return
.end method

; >> READ METHOD <<
.method private static myRead()I
.throws java/io/IOException

.limit stack 5
.limit locals 2

new java/io/BufferedReader
dup
new java/io/InputStreamReader
dup
getstatic java/lang/System/in Ljava/io/InputStream;
invokenonvirtual java/io/InputStreamReader/<init>(Ljava/io/InputStream;)V
invokenonvirtual java/io/BufferedReader/<init>(Ljava/io/Reader;)V
astore_0
aload_0
invokevirtual java/io/BufferedReader/readLine()Ljava/lang/String;
astore_1
aload_1
invokestatic java/lang/Integer/parseInt(Ljava/lang/String;)I
ireturn
.end method

; >> CONSTRUCTOR <<
.method <init>()V
.limit stack 1
.limit locals 1
aload_0
invokenonvirtual java/lang/Object/<init>()V
return
.end method

; >> CLASS INIT FOR GLOBAL ARRAYS <<
.method static <clinit>()V
.limit stack 1
.limit locals 0
return
.end method
--------------------------------------------------------------
if1.c
--------------------------------------------------------------
PURPOSE: test for true statement
OUTCOME:
.source Main.java
.class  synchronized Main
.super  java/lang/Object

; >>FUNCTION MAIN <<
.method public static main([Ljava/lang/String;)V
.throws java/io/IOException
.limit stack 32
.limit locals 32
ldc 1
ifeq Label1
getstatic java/lang/System/out Ljava/io/PrintStream;
ldc 50
invokevirtual java/io/PrintStream/println(I)V
goto Label2
Label1:
getstatic java/lang/System/out Ljava/io/PrintStream;
ldc 100
invokevirtual java/io/PrintStream/println(I)V
Label2:
return
.end method

; >> CONSTRUCTOR <<
.method <init>()V
.limit stack 1
.limit locals 1
aload_0
invokenonvirtual java/lang/Object/<init>()V
return
.end method

; >> CLASS INIT FOR GLOBAL ARRAYS <<
.method static <clinit>()V
.limit stack 1
.limit locals 0
return
.end method
--------------------------------------------------------------
if2.c
--------------------------------------------------------------
PURPOSE: test for false statement
OUTCOME:
.source Main.java
.class  synchronized Main
.super  java/lang/Object

; >>FUNCTION MAIN <<
.method public static main([Ljava/lang/String;)V
.throws java/io/IOException
.limit stack 32
.limit locals 32
ldc 0
ifeq Label1
getstatic java/lang/System/out Ljava/io/PrintStream;
ldc 50
invokevirtual java/io/PrintStream/println(I)V
goto Label2
Label1:
getstatic java/lang/System/out Ljava/io/PrintStream;
ldc 100
invokevirtual java/io/PrintStream/println(I)V
Label2:
return
.end method

; >> CONSTRUCTOR <<
.method <init>()V
.limit stack 1
.limit locals 1
aload_0
invokenonvirtual java/lang/Object/<init>()V
return
.end method

; >> CLASS INIT FOR GLOBAL ARRAYS <<
.method static <clinit>()V
.limit stack 1
.limit locals 0
return
.end method
--------------------------------------------------------------
loop.c
--------------------------------------------------------------
PURPOSE: testing for while loops with one variable as test case
OUTCOME:
.source Main.java
.class  synchronized Main
.super  java/lang/Object

.field static x I
.field static y I
; >>FUNCTION MAIN <<
.method public static main([Ljava/lang/String;)V
.throws java/io/IOException
.limit stack 32
.limit locals 32
ldc 1
putstatic Main/y I
ldc 5
putstatic Main/x I
Label1:
getstatic Main/x I
ifeq Label2
getstatic Main/y I
ldc 2
imul
putstatic Main/y I
getstatic Main/x I
ldc 1
isub
putstatic Main/x I
goto Label1
Label2:
getstatic java/lang/System/out Ljava/io/PrintStream;
getstatic Main/y I
invokevirtual java/io/PrintStream/println(I)V
return
.end method

; >> CONSTRUCTOR <<
.method <init>()V
.limit stack 1
.limit locals 1
aload_0
invokenonvirtual java/lang/Object/<init>()V
return
.end method

; >> CLASS INIT FOR GLOBAL ARRAYS <<
.method static <clinit>()V
.limit stack 1
.limit locals 0
return
.end method
--------------------------------------------------------------
sq.c
--------------------------------------------------------------
PURPOSE: test a function call in main
OUTCOME:
.source Main.java
.class  synchronized Main
.super  java/lang/Object

; >> FUNCTION sq <<
.method static sq(I)V
.limit stack 32
.limit locals 32
iload 0
iload 0
imul
ireturn
return
.end method

; >>FUNCTION MAIN <<
.method public static main([Ljava/lang/String;)V
.throws java/io/IOException
.limit stack 32
.limit locals 32
getstatic java/lang/System/out Ljava/io/PrintStream;
ldc 5
invokestatic Main/sq(I)I
invokevirtual java/io/PrintStream/println(I)V
return
.end method

; >> CONSTRUCTOR <<
.method <init>()V
.limit stack 1
.limit locals 1
aload_0
invokenonvirtual java/lang/Object/<init>()V
return
.end method

; >> CLASS INIT FOR GLOBAL ARRAYS <<
.method static <clinit>()V
.limit stack 1
.limit locals 0
return
.end method
--------------------------------------------------------------
ssort.c 
--------------------------------------------------------------
PURPOSE: test for global variables and nested loops
OUTCOME:
.source Main.java
.class  synchronized Main
.super  java/lang/Object

.field static max I
.field static data [I
.field static i I
.field static j I
.field static mindex I
.field static tmp I
; >>FUNCTION MAIN <<
.method public static main([Ljava/lang/String;)V
.throws java/io/IOException
.limit stack 32
.limit locals 32
ldc 0
putstatic Main/i I
ldc 9
putstatic Main/max I
ldc 9
putstatic Main/j I
Label1:
getstatic Main/i I
getstatic Main/max I
if_icmple Label2
ldc 0
goto Label3
Label2:
ldc 1
Label3:
ifeq Label4
getstatic Main/j I
ldc 10
iadd
putstatic Main/tmp I
getstatic java/lang/System/out Ljava/io/PrintStream;
getstatic Main/tmp I
invokevirtual java/io/PrintStream/println(I)V
getstatic Main/data [I
getstatic Main/i I
getstatic Main/tmp I
iastore 
getstatic Main/j I
ldc 1
isub
putstatic Main/j I
getstatic Main/i I
ldc 1
iadd
putstatic Main/i I
goto Label1
Label4:
ldc 0
putstatic Main/i I
Label5:
getstatic Main/i I
getstatic Main/max I
if_icmple Label6
ldc 0
goto Label7
Label6:
ldc 1
Label7:
ifeq Label8
getstatic Main/i I
putstatic Main/mindex I
getstatic Main/i I
ldc 1
iadd
putstatic Main/j I
Label9:
getstatic Main/j I
getstatic Main/max I
if_icmple Label10
ldc 0
goto Label11
Label10:
ldc 1
Label11:
ifeq Label12
getstatic Main/data [I
getstatic Main/j I
iaload 
getstatic Main/data [I
getstatic Main/mindex I
iaload 
if_icmplt Label13
ldc 0
goto Label14
Label13:
ldc 1
Label14:
ifeq Label15
getstatic Main/j I
putstatic Main/mindex I
goto Label16
Label15:
getstatic Main/mindex I
putstatic Main/mindex I
Label16:
getstatic Main/j I
ldc 1
iadd
putstatic Main/j I
goto Label9
Label12:
getstatic Main/data [I
getstatic Main/mindex I
iaload 
putstatic Main/tmp I
getstatic Main/data [I
getstatic Main/mindex I
getstatic Main/data [I
getstatic Main/i I
iaload 
iastore 
getstatic Main/data [I
getstatic Main/i I
getstatic Main/tmp I
iastore 
getstatic Main/i I
ldc 1
iadd
putstatic Main/i I
goto Label5
Label8:
ldc 0
putstatic Main/i I
Label17:
getstatic Main/i I
getstatic Main/max I
if_icmple Label18
ldc 0
goto Label19
Label18:
ldc 1
Label19:
ifeq Label20
getstatic java/lang/System/out Ljava/io/PrintStream;
getstatic Main/data [I
getstatic Main/i I
iaload 
invokevirtual java/io/PrintStream/println(I)V
getstatic Main/i I
ldc 1
iadd
putstatic Main/i I
goto Label17
Label20:
return
.end method

; >> CONSTRUCTOR <<
.method <init>()V
.limit stack 1
.limit locals 1
aload_0
invokenonvirtual java/lang/Object/<init>()V
return
.end method

; >> CLASS INIT FOR GLOBAL ARRAYS <<
.method static <clinit>()V
.limit stack 1
.limit locals 0
ldc 10
newarray int
putstatic Main/data [I
return
.end method
--------------------------------------------------------------
ssorti.c 
--------------------------------------------------------------
PURPOSE: scanf, nested while statements
OUTCOME:
.source Main.java
.class  synchronized Main
.super  java/lang/Object

.field static max I
.field static data [I
.field static i I
.field static j I
.field static mindex I
.field static tmp I
; >>FUNCTION MAIN <<
.method public static main([Ljava/lang/String;)V
.throws java/io/IOException
.limit stack 32
.limit locals 32
ldc 0
putstatic Main/i I
ldc 9
putstatic Main/max I
ldc 9
putstatic Main/j I
getstatic java/lang/System/out Ljava/io/PrintStream;
ldc 10
invokevirtual java/io/PrintStream/println(I)V
Label1:
getstatic Main/i I
getstatic Main/max I
if_icmple Label2
ldc 0
goto Label3
Label2:
ldc 1
Label3:
ifeq Label4
invokestatic Main/myRead()I
putStatic Main/tmp I
getstatic Main/data [I
getstatic Main/i I
getstatic Main/tmp I
iastore 
getstatic Main/j I
ldc 1
isub
putstatic Main/j I
getstatic Main/i I
ldc 1
iadd
putstatic Main/i I
goto Label1
Label4:
ldc 0
putstatic Main/i I
Label5:
getstatic Main/i I
getstatic Main/max I
if_icmple Label6
ldc 0
goto Label7
Label6:
ldc 1
Label7:
ifeq Label8
getstatic Main/i I
putstatic Main/mindex I
getstatic Main/i I
ldc 1
iadd
putstatic Main/j I
Label9:
getstatic Main/j I
getstatic Main/max I
if_icmple Label10
ldc 0
goto Label11
Label10:
ldc 1
Label11:
ifeq Label12
getstatic Main/data [I
getstatic Main/j I
iaload 
getstatic Main/data [I
getstatic Main/mindex I
iaload 
if_icmplt Label13
ldc 0
goto Label14
Label13:
ldc 1
Label14:
ifeq Label15
getstatic Main/j I
putstatic Main/mindex I
goto Label16
Label15:
getstatic Main/mindex I
putstatic Main/mindex I
Label16:
getstatic Main/j I
ldc 1
iadd
putstatic Main/j I
goto Label9
Label12:
getstatic Main/data [I
getstatic Main/mindex I
iaload 
putstatic Main/tmp I
getstatic Main/data [I
getstatic Main/mindex I
getstatic Main/data [I
getstatic Main/i I
iaload 
iastore 
getstatic Main/data [I
getstatic Main/i I
getstatic Main/tmp I
iastore 
getstatic Main/i I
ldc 1
iadd
putstatic Main/i I
goto Label5
Label8:
ldc 0
putstatic Main/i I
Label17:
getstatic Main/i I
getstatic Main/max I
if_icmple Label18
ldc 0
goto Label19
Label18:
ldc 1
Label19:
ifeq Label20
getstatic java/lang/System/out Ljava/io/PrintStream;
getstatic Main/data [I
getstatic Main/i I
iaload 
invokevirtual java/io/PrintStream/println(I)V
getstatic Main/i I
ldc 1
iadd
putstatic Main/i I
goto Label17
Label20:
return
.end method

; >> READ METHOD <<
.method private static myRead()I
.throws java/io/IOException

.limit stack 5
.limit locals 2

new java/io/BufferedReader
dup
new java/io/InputStreamReader
dup
getstatic java/lang/System/in Ljava/io/InputStream;
invokenonvirtual java/io/InputStreamReader/<init>(Ljava/io/InputStream;)V
invokenonvirtual java/io/BufferedReader/<init>(Ljava/io/Reader;)V
astore_0
aload_0
invokevirtual java/io/BufferedReader/readLine()Ljava/lang/String;
astore_1
aload_1
invokestatic java/lang/Integer/parseInt(Ljava/lang/String;)I
ireturn
.end method

; >> CONSTRUCTOR <<
.method <init>()V
.limit stack 1
.limit locals 1
aload_0
invokenonvirtual java/lang/Object/<init>()V
return
.end method

; >> CLASS INIT FOR GLOBAL ARRAYS <<
.method static <clinit>()V
.limit stack 1
.limit locals 0
ldc 10
newarray int
putstatic Main/data [I
return
.end method
--------------------------------------------------------------
sum.c
--------------------------------------------------------------
PURPOSE: tests while loop using global variables
OUTCOME:
.source Main.java
.class  synchronized Main
.super  java/lang/Object

.field static x I
.field static count I
.field static ans I
; >>FUNCTION MAIN <<
.method public static main([Ljava/lang/String;)V
.throws java/io/IOException
.limit stack 32
.limit locals 32
ldc 10
putstatic Main/x I
ldc 0
putstatic Main/ans I
ldc 0
putstatic Main/count I
Label1:
getstatic Main/count I
getstatic Main/x I
if_icmple Label2
ldc 0
goto Label3
Label2:
ldc 1
Label3:
ifeq Label4
getstatic Main/ans I
getstatic Main/count I
iadd
putstatic Main/ans I
getstatic Main/count I
ldc 1
iadd
putstatic Main/count I
goto Label1
Label4:
getstatic java/lang/System/out Ljava/io/PrintStream;
getstatic Main/ans I
invokevirtual java/io/PrintStream/println(I)V
return
.end method

; >> CONSTRUCTOR <<
.method <init>()V
.limit stack 1
.limit locals 1
aload_0
invokenonvirtual java/lang/Object/<init>()V
return
.end method

; >> CLASS INIT FOR GLOBAL ARRAYS <<
.method static <clinit>()V
.limit stack 1
.limit locals 0
return
.end method
--------------------------------------------------------------
testfile1.txt
--------------------------------------------------------------
PURPOSE: test for while statement, global array
OUTCOME:
.source Main.java
.class  synchronized Main
.super  java/lang/Object

.field static square [I
; >>FUNCTION MAIN <<
.method public static main([Ljava/lang/String;)V
.throws java/io/IOException
.limit stack 32
.limit locals 32
ldc 0
istore 1
Label1:
iload 1
ldc 10
if_icmplt Label2
ldc 0
goto Label3
Label2:
ldc 1
Label3:
ifeq Label4
getstatic Main/square [I
iload 1
iload 2
iload 2
imul
iastore 
iload 2
ldc 1
iadd
istore 2
goto Label1
Label4:
return
.end method

; >> CONSTRUCTOR <<
.method <init>()V
.limit stack 1
.limit locals 1
aload_0
invokenonvirtual java/lang/Object/<init>()V
return
.end method

; >> CLASS INIT FOR GLOBAL ARRAYS <<
.method static <clinit>()V
.limit stack 1
.limit locals 0
ldc 10
newarray int
putstatic Main/square [I
return
.end method
--------------------------------------------------------------
testfile2.txt
--------------------------------------------------------------
PURPOSE: testing for parse errors
OUTCOME:
.source Main.java
.class  synchronized Main
.super  java/lang/Object

; >>FUNCTION MAIN <<
.method public static main([Ljava/lang/String;)V
.throws java/io/IOException
.limit stack 32
.limit locals 32
ldc 2
ldc 2
imul
syntax error, unexpected INT, expecting SEM at line number 7 and column number 2
Compilation error.
--------------------------------------------------------------
testfile3.txt
--------------------------------------------------------------
PURPOSE: testing for semantic errors
OUTCOME:
.source Main.java
.class  synchronized Main
.super  java/lang/Object

; >> FUNCTION foo <<
.method static foo(I)V
.limit stack 32
.limit locals 32
syntax error, unexpected EQUAL, expecting SEM or BLPAR at line number 6 and column number 6
Compilation error.
--------------------------------------------------------------
